devide_spec/__init__.py
devide_spec/main.py
devide_spec/prompts.py
devide_spec-2025.12.21174359.dist-info/METADATA
devide_spec-2025.12.21174359.dist-info/WHEEL
devide_spec-2025.12.21174359.dist-info/top_level.txt
devide_spec-2025.12.21174359.dist-info/RECORD
