Metadata-Version: 2.4
Name: devide-spec
Version: 2025.12.21174359
Summary: A new package that transforms unstructured developer tool ideas from text inputs into structured, actionable product specifications. Users can describe their desired tool in natural language, and the
Author-email: devide-spec <hi@eugene.plus>
License: MIT
Project-URL: Homepage, https://github.com/chigwell/devide-spec
Requires-Python: >=3.9
Requires-Dist: langchain-llm7>=0.0.0
Requires-Dist: llmatch-messages>=0.0.0
Requires-Dist: langchain-core>=0.3.0
